pyKDC101/__init__.py
pyKDC101/core.py
pyKDC101-0.22.dist-info/LICENSE
pyKDC101-0.22.dist-info/METADATA
pyKDC101-0.22.dist-info/WHEEL
pyKDC101-0.22.dist-info/top_level.txt
pyKDC101-0.22.dist-info/RECORD
