Metadata-Version: 2.1
Name: pyKDC101
Version: 0.22
Summary: Functions and examples to control Thorlabs KDC101 through serial commands
Author-email: iancynk <ian.cynk@posteo.eu>
Project-URL: Homepage, https://github.com/iancynk/pyKDC101
Project-URL: Bug Tracker, https://github.com/iancynk/pyKDC101/issues
Classifier: Programming Language :: Python :: 3
Classifier: License :: OSI Approved :: MIT License
Classifier: Operating System :: POSIX :: Linux
Classifier: Intended Audience :: Education
Classifier: Intended Audience :: Science/Research
Classifier: Topic :: Scientific/Engineering
Classifier: Topic :: Scientific/Engineering :: Physics
Classifier: Topic :: Software Development :: Libraries
Classifier: Topic :: Software Development :: Libraries :: Python Modules
Requires-Python: >=3.10
License-File: LICENSE
